chessanalytics/__init__.py
chessanalytics/chessanalytics.py
chessanalytics/chessanalytics_streamlit.py
chessanalytics-1.0.0.dist-info/LICENSE
chessanalytics-1.0.0.dist-info/METADATA
chessanalytics-1.0.0.dist-info/WHEEL
chessanalytics-1.0.0.dist-info/top_level.txt
chessanalytics-1.0.0.dist-info/RECORD
